constructs_tokens_staging/__init__.py
constructs_tokens_staging/py.typed
constructs_tokens_staging/_jsii/__init__.py
constructs_tokens_staging/_jsii/constructs-tokens-staging@0.0.4.jsii.tgz
constructs_tokens_staging-0.0.4.dist-info/METADATA
constructs_tokens_staging-0.0.4.dist-info/WHEEL
constructs_tokens_staging-0.0.4.dist-info/top_level.txt
constructs_tokens_staging-0.0.4.dist-info/RECORD
