Metadata-Version: 2.1
Name: constructs-tokens-staging
Version: 0.0.4
Summary: constructs-tokens-staging
Home-page: https://github.com/iliapolo/constructs-tokens
Author: Eli Polonsky<eli.polonsky@gmail.com>
License: Apache-2.0
Project-URL: Source, https://github.com/iliapolo/constructs-tokens
Platform: UNKNOWN
Classifier: Intended Audience :: Developers
Classifier: Operating System :: OS Independent
Classifier: Programming Language :: JavaScript
Classifier: Programming Language :: Python :: 3 :: Only
Classifier: Programming Language :: Python :: 3.6
Classifier: Programming Language :: Python :: 3.7
Classifier: Programming Language :: Python :: 3.8
Classifier: Typing :: Typed
Classifier: Development Status :: 5 - Production/Stable
Classifier: License :: OSI Approved
Requires-Python: >=3.6
Requires-Dist: jsii (<2.0.0,>=1.9.0)
Requires-Dist: publication (>=0.0.3)
Requires-Dist: constructs (<4.0.0,>=3.0.4)
